MANIFEST.in
README.txt
setup.cfg
setup.py
BurnerOnFire.egg-info/PKG-INFO
BurnerOnFire.egg-info/SOURCES.txt
BurnerOnFire.egg-info/dependency_links.txt
BurnerOnFire.egg-info/entry_points.txt
BurnerOnFire.egg-info/not-zip-safe
BurnerOnFire.egg-info/requires.txt
BurnerOnFire.egg-info/top_level.txt
burneronfire/LICENSE.txt
burneronfire/__init__.py
burneronfire/gui.py
burneronfire/utils.py
burneronfire/icons/burneronfire_logo.png
burneronfire/icons/burnthem.png
burneronfire/icons/favicon.png
burneronfire/icons/logfile.png
docs/Makefile
docs/build/doctrees/environment.pickle
docs/build/doctrees/index.doctree
docs/build/html/.buildinfo
docs/build/html/genindex.html
docs/build/html/index.html
docs/build/html/modindex.html
docs/build/html/objects.inv
docs/build/html/search.html
docs/build/html/searchindex.js
docs/build/html/_images/gui_main.png
docs/build/html/_sources/index.txt
docs/build/html/_static/basic.css
docs/build/html/_static/burneronfire_logo.png
docs/build/html/_static/default.css
docs/build/html/_static/doctools.js
docs/build/html/_static/file.png
docs/build/html/_static/flowchart.jpg
docs/build/html/_static/jquery.js
docs/build/html/_static/minus.png
docs/build/html/_static/plus.png
docs/build/html/_static/pygments.css
docs/build/html/_static/searchtools.js
docs/source/burneronfire_logo.png
docs/source/conf.py
docs/source/gui_main.png
docs/source/index.rst
docs/source/_static/flowchart.jpg