Metadata-Version: 1.0
Name: BurnerOnFire
Version: 0.1
Summary: BurnerOnFire is multi-threaded program that can write same content (iso files for now) to multiple CD/DVD burners simultaneously.
Home-page: http://www.kiberpipa.org/burneronfire/
Author: Domen Kozar
Author-email: domen@dev.si
License: BSD
Keywords: cd dvd burn burner pygtk
Platform: UNKNOWN
Classifier: Development Status :: 5 - Production/Stable
Classifier: Environment :: X11 Applications :: GTK
Classifier: License :: OSI Approved :: BSD License
Classifier: Operating System :: POSIX :: Linux
Classifier: Programming Language :: Python
